MANIFEST.in
README.rst
setup.py
django_blakey_utils/__init__.py
django_blakey_utils.egg-info/PKG-INFO
django_blakey_utils.egg-info/SOURCES.txt
django_blakey_utils.egg-info/dependency_links.txt
django_blakey_utils.egg-info/requires.txt
django_blakey_utils.egg-info/top_level.txt
django_blakey_utils/assert_utils/__init__.py
django_blakey_utils/md_utils/__init__.py
django_blakey_utils/re_utils/__init__.py
django_blakey_utils/string_utils/__init__.py
django_blakey_utils/test_utils/__init__.py
django_blakey_utils/test_utils/tastypie_test.py
django_blakey_utils/test_utils/utils.py
django_blakey_utils/url_utils/__init__.py