Metadata-Version: 1.1
Name: django-blakey-utils
Version: 0.0.11-pre-alpha
Summary: Common utilities for Blakey project
Home-page: https://github.com/tangentlabs/django-blakey-utils
Author: Tangent Labs
Author-email: mariia.sakharova@tangentlabs.co.uk
License: BSD
Keywords: Utilities,Blakey
Platform: linux
Classifier: Development Status :: 1 - Planning
Classifier: Intended Audience :: Developers
Classifier: License :: OSI Approved :: BSD License
Classifier: Operating System :: Unix
Classifier: Programming Language :: Python
